[
  {
    "label": "elyp3_rb2_parent",
    "kind": "rb2",
    "params": {"fc_setpoint": 0.574, "ely_setpoint": 0.465},
    "model": {"ely": {"stress_exponent": 3.0}}
  },
  {
    "label": "elyp3_rb1_best25",
    "kind": "rb1",
    "params": {"soc_low": 0.20, "soc_high": 0.37},
    "model": {"ely": {"stress_exponent": 3.0}}
  },
  {
    "label": "elyp3_rb2_soh_best25",
    "kind": "rb2_soh",
    "params": {
      "fc_setpoint": 0.574,
      "ely_setpoint": 0.465,
      "fc_self": -0.0125,
      "shape": 4.0,
      "soh_source": "permanent"
    },
    "model": {"ely": {"stress_exponent": 3.0}}
  }
]
